{"nm":"scroll line animation","ddd":0,"h":500,"w":125,"meta":{"g":"LottieFiles AE 3.5.4"},"layers":[{"ty":4,"nm":"シェイプレイヤー 3","sr":1,"st":0,"op":120.0000048877,"ip":0,"hd":false,"ddd":0,"bm":0,"hasMask":false,"ao":0,"ks":{"a":{"a":0,"k":[0,0,0],"ix":1},"s":{"a":0,"k":[100,100,100],"ix":6},"sk":{"a":0,"k":0},"p":{"a":0,"k":[58.5,267,0],"ix":2},"r":{"a":0,"k":0,"ix":10},"sa":{"a":0,"k":0},"o":{"a":0,"k":100,"ix":11}},"ef":[],"shapes":[{"ty":"gr","bm":0,"hd":false,"mn":"ADBE Vector Group","nm":"シェイプ 1","ix":1,"cix":2,"np":3,"it":[{"ty":"sh","bm":0,"hd":false,"mn":"ADBE Vector Shape - Group","nm":"パス 1","ix":1,"d":1,"ks":{"a":0,"k":{"c":false,"i":[[0,0],[0,0]],"o":[[0,0],[0,0]],"v":[[4,-257.5],[4,225.5]]},"ix":2}},{"ty":"st","bm":0,"hd":false,"mn":"ADBE Vector Graphic - Stroke","nm":"線 1","lc":2,"lj":1,"ml":4,"o":{"a":0,"k":100,"ix":4},"w":{"a":0,"k":5,"ix":5},"c":{"a":0,"k":[0,0,0],"ix":3}},{"ty":"fl","bm":0,"hd":false,"mn":"ADBE Vector Graphic - Fill","nm":"塗り 1","c":{"a":0,"k":[0,0,0],"ix":4},"r":1,"o":{"a":0,"k":100,"ix":5}},{"ty":"tr","a":{"a":0,"k":[0,0],"ix":1},"s":{"a":0,"k":[100,100],"ix":3},"sk":{"a":0,"k":0,"ix":4},"p":{"a":0,"k":[0,0],"ix":2},"r":{"a":0,"k":0,"ix":6},"sa":{"a":0,"k":0,"ix":5},"o":{"a":0,"k":100,"ix":7}}]},{"ty":"tm","bm":0,"hd":false,"mn":"ADBE Vector Filter - Trim","nm":"パスのトリミング 1","ix":2,"e":{"a":1,"k":[{"o":{"x":0.773,"y":0},"i":{"x":0.372,"y":1},"s":[0],"t":0},{"s":[100],"t":30.0000012219251}],"ix":2},"o":{"a":0,"k":0,"ix":3},"s":{"a":1,"k":[{"o":{"x":0.333,"y":0},"i":{"x":0.205,"y":1},"s":[0],"t":34},{"s":[100],"t":64.0000026067734}],"ix":1},"m":1}],"ind":1}],"v":"4.8.0","fr":59.9400024414062,"op":120.0000048877,"ip":0,"assets":[]}